src/sumador-restador/sumador_1bit.v
// Módulo: Sumador completo de 1 bit (Full Adder)
module sumador_1bit (
    input A,
    input B,
    input Cin,
    output So,
    output Cout
);
    // Lógica del sumador de 1 bit
    assign So = A ^ B ^ Cin;               // Suma
    assign Cout = (A & B) | (Cin & (A ^ B)); // Acarreo de salida
endmodule

src/sumador-restador/sumador_restador_4bit.v
// Módulo: Sumador/Restador de 4 bits
module sumador_restador_4bit (
    input [3:0] A,      // Entrada A de 4 bits
    input [3:0] B,      // Entrada B de 4 bits
    input Sel,          // Selector: 0 = Suma, 1 = Resta
    output [3:0] So,    // Resultado de 4 bits
    output Co           // Acarreo final de salida
);

    // Cables internos para las salidas de las compuertas XOR
    wire [3:0] B_xor;
    
    // Cables internos para los acarreos entre sumadores (C0, C1, C2)
    wire C0, C1, C2;

    // Compuertas XOR: Invierten B si Sel es 1 (Complemento a 1)
    // Si Sel es 0, dejan pasar B intacto.
    assign B_xor[0] = B[0] ^ Sel;
    assign B_xor[1] = B[1] ^ Sel;
    assign B_xor[2] = B[2] ^ Sel;
    assign B_xor[3] = B[3] ^ Sel;

    // Instancia 0 (Bit menos significativo)
    // Nota: El Cin de este sumador está conectado directamente a 'Sel'
    sumador_1bit sum0 (
        .A(A[0]),
        .B(B_xor[0]),
        .Cin(Sel),       // Aquí se suma el +1 para el complemento a 2 cuando Sel=1
        .So(So[0]),
        .Cout(C0)
    );

    // Instancia 1
    sumador_1bit sum1 (
        .A(A[1]),
        .B(B_xor[1]),
        .Cin(C0),        // Acarreo de la etapa anterior
        .So(So[1]),
        .Cout(C1)
    );

    // Instancia 2
    sumador_1bit sum2 (
        .A(A[2]),
        .B(B_xor[2]),
        .Cin(C1),
        .So(So[2]),
        .Cout(C2)
    );

    // Instancia 3 (Bit más significativo)
    sumador_1bit sum3 (
        .A(A[3]),
        .B(B_xor[3]),
        .Cin(C2),
        .So(So[3]),
        .Cout(Co)        // Acarreo final
    );

endmodule

sim/tb_sumador_restador_4bit.v
`timescale 1ns / 1ps

module tb_sumador_restador_4bit;

    // Declaración de señales
    reg [3:0] A;
    reg [3:0] B;
    reg Sel;
    wire [3:0] So;
    wire Co;

    // Instanciar el circuito principal
    sumador_restador_4bit dut (
        .A(A),
        .B(B),
        .Sel(Sel),
        .So(So),
        .Co(Co)
    );

    // Estímulos de prueba
    initial begin
        // Generar archivo para ver gráficas de ondas
        $dumpfile("ondas.vcd");
        $dumpvars(0, tb_sumador_restador_4bit);

        $display("--------------------------------------------------");
        $display("Sel | A (bin) | B (bin) | Co | So (bin) | Operacion ");
        $display("--------------------------------------------------");
        $monitor(" %b  |   %b  |   %b  |  %b |   %b   ", Sel, A, B, Co, So);

        // --- 6 CASOS DE SUMA (Sel = 0) ---
        Sel = 0; 
        
        A = 4'b0011; B = 4'b0100; #10; // 1. 3 + 4 = 7
        A = 4'b0101; B = 4'b0010; #10; // 2. 5 + 2 = 7
        A = 4'b1000; B = 4'b0001; #10; // 3. 8 + 1 = 9
        A = 4'b0111; B = 4'b0111; #10; // 4. 7 + 7 = 14
        A = 4'b0000; B = 4'b0101; #10; // 5. 0 + 5 = 5
        A = 4'b1010; B = 4'b0101; #10; // 6. 10 + 5 = 15

        $display("--------------------------------------------------");

        // --- 6 CASOS DE RESTA (Sel = 1) ---
        Sel = 1; 

        A = 4'b0111; B = 4'b0101; #10; // 1. 7 - 5 = 2  (Positivo, Co=1)
        A = 4'b0011; B = 4'b0111; #10; // 2. 3 - 7 = -4 (Negativo, Compl. a 2, Co=0)
        A = 4'b1000; B = 4'b0100; #10; // 3. 8 - 4 = 4  (Positivo, Co=1)
        A = 4'b1010; B = 4'b1010; #10; // 4. 10 - 10 = 0 (Cero, Co=1)
        A = 4'b0101; B = 4'b1000; #10; // 5. 5 - 8 = -3 (Negativo, Compl. a 2, Co=0)
        A = 4'b1111; B = 4'b0001; #10; // 6. 15 - 1 = 14 (Positivo, Co=1)

        // Terminar la simulación
        $finish;
    end

endmodule

sim/ondas.vcd
$date
	Wed Feb 25 20:51:44 2026
$end
$version
	Icarus Verilog
$end
$timescale
	1ps
$end
$scope module tb_sumador_restador_4bit $end
$var wire 4 ! So [3:0] $end
$var wire 1 " Co $end
$var reg 4 # A [3:0] $end
$var reg 4 $ B [3:0] $end
$var reg 1 % Sel $end
$scope module dut $end
$var wire 4 & A [3:0] $end
$var wire 4 ' B [3:0] $end
$var wire 1 % Sel $end
$var wire 4 ( So [3:0] $end
$var wire 1 " Co $end
$var wire 1 ) C2 $end
$var wire 1 * C1 $end
$var wire 1 + C0 $end
$var wire 4 , B_xor [3:0] $end
$scope module sum0 $end
$var wire 1 - A $end
$var wire 1 . B $end
$var wire 1 % Cin $end
$var wire 1 + Cout $end
$var wire 1 / So $end
$upscope $end
$scope module sum1 $end
$var wire 1 0 A $end
$var wire 1 1 B $end
$var wire 1 + Cin $end
$var wire 1 * Cout $end
$var wire 1 2 So $end
$upscope $end
$scope module sum2 $end
$var wire 1 3 A $end
$var wire 1 4 B $end
$var wire 1 * Cin $end
$var wire 1 ) Cout $end
$var wire 1 5 So $end
$upscope $end
$scope module sum3 $end
$var wire 1 6 A $end
$var wire 1 7 B $end
$var wire 1 ) Cin $end
$var wire 1 " Cout $end
$var wire 1 8 So $end
$upscope $end
$upscope $end
$upscope $end
$enddefinitions $end
$comment Show the parameter values. $end
$dumpall
$end
#0
$dumpvars
08
07
06
15
14
03
12
01
10
1/
0.
1-
b100 ,
0+
0*
0)
b111 (
b100 '
b11 &
0%
b100 $
b11 #
0"
b111 !
$end
#10000
08
11
04
12
b111 !
b111 (
15
0)
b10 ,
00
13
b10 $
b10 '
b101 #
b101 &
#20000
02
1.
01
1/
05
b1001 !
b1001 (
18
b1 ,
0-
03
16
b1 $
b1 '
b1000 #
b1000 &
#30000
1)
1*
11
14
0/
1+
12
15
b1110 !
b1110 (
18
b111 ,
1-
10
13
06
b111 $
b111 '
b111 #
b111 &
#40000
08
0)
0*
01
1/
0+
02
b101 !
b101 (
15
b101 ,
0-
00
03
b101 $
b101 '
b0 #
b0 &
#50000
12
b1111 !
b1111 (
18
10
16
b1010 #
b1010 &
#60000
1"
08
1)
05
1*
12
0.
11
04
17
1+
1-
13
06
b1010 ,
b10 !
b10 (
0/
b111 #
b111 &
1%
#70000
0"
02
18
0)
01
b1100 !
b1100 (
15
b1000 ,
03
b111 $
b111 '
b11 #
b11 &
#80000
15
1+
1*
1.
11
0/
02
b100 !
b100 (
08
1"
b1011 ,
0-
00
16
b100 $
b100 '
b1000 #
b1000 &
#90000
1)
05
08
1"
01
14
07
b0 !
b0 (
02
b101 ,
10
b1010 $
b1010 '
b1010 #
b1010 &
#100000
1*
0"
11
1/
02
15
b1101 !
b1101 (
18
b111 ,
1-
00
13
06
b1000 $
b1000 '
b101 #
b101 &
#110000
0/
1"
0.
17
12
b1110 !
b1110 (
18
b1110 ,
10
16
b1 $
b1 '
b1111 #
b1111 &
